imgw_data/__about__.py
imgw_data/__init__.py
imgw_data/consts.py
imgw_data/get.py
imgw_data/stations.py
imgw_data/export/__init__.py
imgw_data/export/export.py
imgw_data/utils/__init__.py
imgw_data/utils/parse.py
imgw_data/utils/translate.py
imgw_data/utils/urljoin.py
imgw_data-0.1.4.dist-info/METADATA
imgw_data-0.1.4.dist-info/WHEEL
imgw_data-0.1.4.dist-info/licenses/LICENSE
imgw_data-0.1.4.dist-info/RECORD
