Metadata-Version: 2.3
Name: imgw-data
Version: 0.1.4
Summary: Python API for public IMGW data - atmospheric measurement from Polish weather stations
Project-URL: Documentation, https://github.com/SimonMolinsky/imgw-data-loader#readme
Project-URL: Issues, https://github.com/SimonMolinsky/imgw-data-loader/issues
Project-URL: Source, https://github.com/SimonMolinsky/imgw-data-loader
Author-email: Szymon Moliński <simon@ml-gis-service.com>
License-Expression: BSD-3-Clause
License-File: LICENSE
Keywords: api,atmospheric science,poland,weather,weather stations
Classifier: Development Status :: 4 - Beta
Classifier: Intended Audience :: Science/Research
Classifier: Programming Language :: Python
Classifier: Programming Language :: Python :: 3.8
Classifier: Programming Language :: Python :: 3.9
Classifier: Programming Language :: Python :: 3.10
Classifier: Programming Language :: Python :: 3.11
Classifier: Programming Language :: Python :: 3.12
Classifier: Topic :: Scientific/Engineering
Classifier: Topic :: Scientific/Engineering :: Atmospheric Science
Classifier: Topic :: Scientific/Engineering :: GIS
Classifier: Topic :: Utilities
Requires-Python: >=3.8
Requires-Dist: requests
